wiliot_testers/API_README.md
wiliot_testers/__init__.py
wiliot_testers/requirements.txt
wiliot_testers/tester_utils.py
wiliot_testers/upload_testers_data.bat
wiliot_testers/upload_testers_data_to_cloud.py
wiliot_testers/version.py
wiliot_testers/wiliot_tester_log.py
wiliot_testers/wiliot_tester_tag_result.py
wiliot_testers/wiliot_tester_tag_test.py
wiliot_testers/association_tester/__init__.py
wiliot_testers/association_tester/association_and_verification_tester.py
wiliot_testers/association_tester/run_association_and_verification_tester.bat
wiliot_testers/association_tester/configs/__init__.py
wiliot_testers/association_tester/configs/cognex_l2r_2codes_1bar_1qr.dmb
wiliot_testers/association_tester/configs/packets_configs.py
wiliot_testers/association_tester/hw_components/__init__.py
wiliot_testers/association_tester/hw_components/r2r_component.py
wiliot_testers/association_tester/hw_components/scanner_component.py
wiliot_testers/association_tester/modules/__init__.py
wiliot_testers/association_tester/modules/association_module.py
wiliot_testers/association_tester/modules/configuration_module.py
wiliot_testers/association_tester/modules/gui_module.py
wiliot_testers/association_tester/modules/performance_module.py
wiliot_testers/association_tester/utils/__init__.py
wiliot_testers/association_tester/utils/continuous_scan.py
wiliot_testers/association_tester/utils/manual_removal.py
wiliot_testers/association_tester/utils/run_contiuous_scan.bat
wiliot_testers/calibration_test/__init__.py
wiliot_testers/calibration_test/calibration_test.py
wiliot_testers/calibration_test/calibration_test_by_tbp.py
wiliot_testers/config/__init__.py
wiliot_testers/config/equipment_config.json
wiliot_testers/config/unusable_inlays.py
wiliot_testers/docs/__init__.py
wiliot_testers/docs/tester_api_flow.pdf
wiliot_testers/docs/wiliot_logo.png
wiliot_testers/examples/__init__.py
wiliot_testers/examples/wiliot_tester_example.py
wiliot_testers/failure_analysis_tester/__init__.py
wiliot_testers-5.11.1.dist-info/LICENSE
wiliot_testers-5.11.1.dist-info/METADATA
wiliot_testers-5.11.1.dist-info/WHEEL
wiliot_testers-5.11.1.dist-info/top_level.txt
wiliot_testers-5.11.1.dist-info/RECORD
