Metadata-Version: 2.1
Name: wiliot_testers
Version: 5.11.1
Summary: A library for interacting with Wiliot's Testers app
Home-page: 
Author: Wiliot
Author-email: support@wiliot.com
License: MIT
Project-URL: Bug Tracker, https://WILIOT-ZENDESK-URL
Classifier: Programming Language :: Python :: 3
Classifier: License :: OSI Approved :: MIT License
Classifier: Operating System :: OS Independent
Requires-Python: >=3.6
License-File: LICENSE
Requires-Dist: setuptools-scm
Requires-Dist: pyqtgraph
Requires-Dist: dash (<=2.18.2)
Requires-Dist: dash-bootstrap-components
Requires-Dist: dash-daq
Requires-Dist: wiliot-api (>=4.10.14)
Requires-Dist: wiliot-core (>=5.12.1)
Requires-Dist: wiliot-tools (>=4.12.0)
Requires-Dist: wiliot-test-equipment (>=1.0.1)
Requires-Dist: PyQt5-sip (==12.9.0) ; python_version < "3.11"
Requires-Dist: PyQt5 (==5.15.6) ; python_version < "3.11"
Requires-Dist: PyQt5-sip ; python_version >= "3.11"
Requires-Dist: PyQt5 ; python_version >= "3.11"
